Workbook

Sheet INPUTS
A1: インプット（変数設定）
A2: 物件価格 | B2: 100000000 | C2: 円 | E2: ※割合・率は 0～1 の小数で入力（例：5% → 0.05）。単位はC列参照。
A3: 建物価格割合 | B3: 0.5
A4: 土地価格割合 | B4: =1-B3 -> 0.5
A5: 建物法定耐用年数 | B5: 7 | C5: 年 | E5: 鉄骨造34年の20%
A6: 頭金割合 | B6: 0.05
A7: 借入割合 | B7: 0.95
A8: 利回り（想定） | B8: 0.09
A9: 家賃下落率 | B9: 0.01
A10: 空室率（％） | B10: 0.05
A11: 管理費（％/家賃） | B11: 0.15
A12: その他経費（％/家賃） | B12: 0.05
A13: 役員報酬（円） | B13: 0.03
A14: 借入期間（年） | B14: 35 | C14: 年
A15: 金利（％） | B15: 0.033
A16: 法人税等実効税率 | B16: 0.23
A18: 【仕様メモ】
A19: ・借入：元金均等（借入額/借入期間）。利息=期首残×金利。
A20: ・家賃：物件価格×利回り×(1-家賃下落率)^(年-1)×(1-空室率)。
A21: ・管理費/その他：家賃に対する％（B列は小数入力、C列に％表記）。
A22: ・減価償却：建物（価格×建物割合）を定額で耐用年数按分。
A23: ・役員報酬：固定額。
A24: ・税金：MAX(税引前利益,0)×実効税率。
A25: ・FCF：税引後利益＋減価償却?元本返済。

Sheet OUTPUT
A1: 不動産投資シミュレーション（OUTPUT）
A2: 上：簡易PL／中：簡易CF／下：簡易BS（横=年次 1～20年）
B3: 項目＼年 | C3: 1年目 | D3: 2年目 | E3: 3年目 | F3: 4年目 | G3: 5年目 | H3: 6年目 | I3: 7年目 | J3: 8年目 | K3: 9年目 | L3: 10年目 | M3: 11年目 | N3: 12年目 | O3: 13年目 | P3: 14年目 | Q3: 15年目 | R3: 16年目 | S3: 17年目 | T3: 18年目 | U3: 19年目 | V3: 20年目
B4: 家賃収入 | C4: =INPUTS!$B$2*INPUTS!$B$8*(1-INPUTS!$B$9)^0*(1-INPUTS!$B$10) -> 8550000 | D4: =INPUTS!$B$2*INPUTS!$B$8*(1-INPUTS!$B$9)^1*(1-INPUTS!$B$10) -> 8464500 | E4: =INPUTS!$B$2*INPUTS!$B$8*(1-INPUTS!$B$9)^2*(1-INPUTS!$B$10) -> 8379855 | F4: =INPUTS!$B$2*INPUTS!$B$8*(1-INPUTS!$B$9)^3*(1-INPUTS!$B$10) -> 8296056.4 | G4: =INPUTS!$B$2*INPUTS!$B$8*(1-INPUTS!$B$9)^4*(1-INPUTS!$B$10) -> 8213095.9 | H4: =INPUTS!$B$2*INPUTS!$B$8*(1-INPUTS!$B$9)^5*(1-INPUTS!$B$10) -> 8130964.9 | I4: =INPUTS!$B$2*INPUTS!$B$8*(1-INPUTS!$B$9)^6*(1-INPUTS!$B$10) -> 8049655.3 | J4: =INPUTS!$B$2*INPUTS!$B$8*(1-INPUTS!$B$9)^7*(1-INPUTS!$B$10) -> 7969158.7 | K4: =INPUTS!$B$2*INPUTS!$B$8*(1-INPUTS!$B$9)^8*(1-INPUTS!$B$10) -> 7889467.1 | L4: =INPUTS!$B$2*INPUTS!$B$8*(1-INPUTS!$B$9)^9*(1-INPUTS!$B$10) -> 7810572.5 | M4: =INPUTS!$B$2*INPUTS!$B$8*(1-INPUTS!$B$9)^10*(1-INPUTS!$B$10) -> 7732466.7 | N4: =INPUTS!$B$2*INPUTS!$B$8*(1-INPUTS!$B$9)^11*(1-INPUTS!$B$10) -> 7655142.1 | O4: =INPUTS!$B$2*INPUTS!$B$8*(1-INPUTS!$B$9)^12*(1-INPUTS!$B$10) -> 7578590.7 | P4: =INPUTS!$B$2*INPUTS!$B$8*(1-INPUTS!$B$9)^13*(1-INPUTS!$B$10) -> 7502804.7 | Q4: =INPUTS!$B$2*INPUTS!$B$8*(1-INPUTS!$B$9)^14*(1-INPUTS!$B$10) -> 7427776.7 | R4: =INPUTS!$B$2*INPUTS!$B$8*(1-INPUTS!$B$9)^15*(1-INPUTS!$B$10) -> 7353498.9 | S4: =INPUTS!$B$2*INPUTS!$B$8*(1-INPUTS!$B$9)^16*(1-INPUTS!$B$10) -> 7279963.9 | T4: =INPUTS!$B$2*INPUTS!$B$8*(1-INPUTS!$B$9)^17*(1-INPUTS!$B$10) -> 7207164.3 | U4: =INPUTS!$B$2*INPUTS!$B$8*(1-INPUTS!$B$9)^18*(1-INPUTS!$B$10) -> 7135092.7 | V4: =INPUTS!$B$2*INPUTS!$B$8*(1-INPUTS!$B$9)^19*(1-INPUTS!$B$10) -> 7063741.7
B5: 管理費 | C5: =C4*INPUTS!$B$11 -> 1282500 | D5: =D4*INPUTS!$B$11 -> 1269675 | E5: =E4*INPUTS!$B$11 -> 1256978.2 | F5: =F4*INPUTS!$B$11 -> 1244408.5 | G5: =G4*INPUTS!$B$11 -> 1231964.4 | H5: =H4*INPUTS!$B$11 -> 1219644.7 | I5: =I4*INPUTS!$B$11 -> 1207448.3 | J5: =J4*INPUTS!$B$11 -> 1195373.8 | ... V5: =V4*INPUTS!$B$11 -> 1059561.3
B6: その他経費 | C6: =C4*INPUTS!$B$12 -> 427500 | D6: =D4*INPUTS!$B$12 -> 423225 | E6: =E4*INPUTS!$B$12 -> 418992.75 | F6: =F4*INPUTS!$B$12 -> 414802.82 | G6: =G4*INPUTS!$B$12 -> 410654.79 | H6: =H4*INPUTS!$B$12 -> 406548.25 | I6: =I4*INPUTS!$B$12 -> 402482.76 | J6: =J4*INPUTS!$B$12 -> 398457.94 | ... V6: =V4*INPUTS!$B$12 -> 353187.09
B7: 役員報酬 | C7: =C4*INPUTS!$B$13 -> 256500 | D7: =D4*INPUTS!$B$13 -> 253935 | E7: =E4*INPUTS!$B$13 -> 251395.65 | F7: =F4*INPUTS!$B$13 -> 248881.69 | G7: =G4*INPUTS!$B$13 -> 246392.88 | H7: =H4*INPUTS!$B$13 -> 243928.95 | I7: =I4*INPUTS!$B$13 -> 241489.66 | J7: =J4*INPUTS!$B$13 -> 239074.76 | ... V7: =V4*INPUTS!$B$13 -> 211912.25
B8: 減価償却費 | C8: =INPUTS!$B$2*INPUTS!$B$3/INPUTS!$B$5 -> 7142857.1 | D8: =INPUTS!$B$2*INPUTS!$B$3/INPUTS!$B$5 -> 7142857.1 | E8: =INPUTS!$B$2*INPUTS!$B$3/INPUTS!$B$5 -> 7142857.1 | F8: =INPUTS!$B$2*INPUTS!$B$3/INPUTS!$B$5 -> 7142857.1 | G8: =INPUTS!$B$2*INPUTS!$B$3/INPUTS!$B$5 -> 7142857.1 | H8: =INPUTS!$B$2*INPUTS!$B$3/INPUTS!$B$5 -> 7142857.1 | I8: =INPUTS!$B$2*INPUTS!$B$3/INPUTS!$B$5 -> 7142857.1
B9: 支払利息 | C9: =C21*INPUTS!$B$15 -> 3135000 | D9: =D21*INPUTS!$B$15 -> 3045428.6 | E9: =E21*INPUTS!$B$15 -> 2955857.1 | F9: =F21*INPUTS!$B$15 -> 2866285.7 | G9: =G21*INPUTS!$B$15 -> 2776714.3 | H9: =H21*INPUTS!$B$15 -> 2687142.9 | I9: =I21*INPUTS!$B$15 -> 2597571.4 | J9: =J21*INPUTS!$B$15 -> 2508000 | ... V9: =V21*INPUTS!$B$15 -> 1433142.9
B10: 税引前利益 | C10: =C4-C5-C6-C7-C8-C9 -> -3694357.1 | D10: =D4-D5-D6-D7-D8-D9 -> -3670620.7 | E10: =E4-E5-E6-E7-E8-E9 -> -3646225.9 | F10: =F4-F5-F6-F7-F8-F9 -> -3621179.4 | G10: =G4-G5-G6-G7-G8-G9 -> -3595487.6 | H10: =H4-H5-H6-H7-H8-H9 -> -3569157 | I10: =I4-I5-I6-I7-I8-I9 -> -3542194 | J10: =J4-J5-J6-J7-J8-J9 -> 3628252.2 | ... V10: =V4-V5-V6-V7-V8-V9 -> 4005938.3
B11: 法人税等 | C11: =MAX(C10,0)*INPUTS!$B$16 -> 0 | D11: =MAX(D10,0)*INPUTS!$B$16 -> 0 | E11: =MAX(E10,0)*INPUTS!$B$16 -> 0 | F11: =MAX(F10,0)*INPUTS!$B$16 -> 0 | G11: =MAX(G10,0)*INPUTS!$B$16 -> 0 | H11: =MAX(H10,0)*INPUTS!$B$16 -> 0 | I11: =MAX(I10,0)*INPUTS!$B$16 -> 0 | J11: =MAX(J10,0)*INPUTS!$B$16 -> 834498.01 | ... V11: =MAX(V10,0)*INPUTS!$B$16 -> 921365.8
B12: 税引後利益 | C12: =C10-C11 -> -3694357.1 | D12: =D10-D11 -> -3670620.7 | E12: =E10-E11 -> -3646225.9 | F12: =F10-F11 -> -3621179.4 | G12: =G10-G11 -> -3595487.6 | H12: =H10-H11 -> -3569157 | I12: =I10-I11 -> -3542194 | J12: =J10-J11 -> 2793754.2 | ... V12: =V10-V11 -> 3084572.5
B14: 簡易CF
B15: 税引後利益 | C15: =C12 -> -3694357.1 | D15: =D12 -> -3670620.7 | E15: =E12 -> -3646225.9 | F15: =F12 -> -3621179.4 | G15: =G12 -> -3595487.6 | H15: =H12 -> -3569157 | I15: =I12 -> -3542194 | J15: =J12 -> 2793754.2 | ... V15: =V12 -> 3084572.5
B16: 減価償却費（非資金） | C16: =C8 -> 7142857.1 | D16: =D8 -> 7142857.1 | E16: =E8 -> 7142857.1 | F16: =F8 -> 7142857.1 | G16: =G8 -> 7142857.1 | H16: =H8 -> 7142857.1 | I16: =I8 -> 7142857.1 | J16: =J8 -> 0 | ... V16: =V8 -> 0
B17: 元本返済（資金流出） | C17: =INPUTS!$B$2*INPUTS!$B$7/INPUTS!$B$14 -> 2714285.7 | D17: =INPUTS!$B$2*INPUTS!$B$7/INPUTS!$B$14 -> 2714285.7 | E17: =INPUTS!$B$2*INPUTS!$B$7/INPUTS!$B$14 -> 2714285.7 | F17: =INPUTS!$B$2*INPUTS!$B$7/INPUTS!$B$14 -> 2714285.7 | G17: =INPUTS!$B$2*INPUTS!$B$7/INPUTS!$B$14 -> 2714285.7 | H17: =INPUTS!$B$2*INPUTS!$B$7/INPUTS!$B$14 -> 2714285.7 | I17: =INPUTS!$B$2*INPUTS!$B$7/INPUTS!$B$14 -> 2714285.7 | J17: =INPUTS!$B$2*INPUTS!$B$7/INPUTS!$B$14 -> 2714285.7 | ... V17: =INPUTS!$B$2*INPUTS!$B$7/INPUTS!$B$14 -> 2714285.7
B18: FCF | C18: =C15+C16-C17 -> 734214.29 | D18: =D15+D16-D17 -> 757950.71 | E18: =E15+E16-E17 -> 782345.49 | F18: =F15+F16-F17 -> 807392.04 | G18: =G15+G16-G17 -> 833083.83 | H18: =H15+H16-H17 -> 859414.42 | I18: =I15+I16-I17 -> 886377.42 | J18: =J15+J16-J17 -> 79468.494 | ... V18: =V15+V16-V17 -> 370286.76
B20: 簡易BS
B21: 期首借入金残高 | C21: =INPUTS!$B$2*INPUTS!$B$7 -> 95000000 | D21: =OFFSET(D21,1,-1) -> 92285714 | E21: =OFFSET(E21,1,-1) -> 89571429 | F21: =OFFSET(F21,1,-1) -> 86857143 | G21: =OFFSET(G21,1,-1) -> 84142857 | H21: =OFFSET(H21,1,-1) -> 81428571 | I21: =OFFSET(I21,1,-1) -> 78714286 | J21: =OFFSET(J21,1,-1) -> 76000000 | K21: =OFFSET(K21,1,-1) -> 73285714 | ... V21: =OFFSET(V21,1,-1) -> 43428571
B22: 期末借入金残高 | C22: =C21-C17 -> 92285714 | D22: =D21-D17 -> 89571429 | E22: =E21-E17 -> 86857143 | F22: =F21-F17 -> 84142857 | G22: =G21-G17 -> 81428571 | H22: =H21-H17 -> 78714286 | I22: =I21-I17 -> 76000000 | J22: =J21-J17 -> 73285714 | ... V22: =V21-V17 -> 40714286

Sheet 返済シュミレーション (3)
C2: 借入金額 | D2: 5000 | E2: 万円 | I2: 借入金額 | J2: 5000 | K2: 万円
C3: 金利 | D3: 0.043 | I3: 金利 | J3: 0.022
C4: 返済期間 | D4: 25 | E4: 年 | I4: 返済期間 | J4: 25 | K4: 年
C5: 毎月返済額 | D5: =INT(PMT(D3/12,D4*12,-D2*10000)) -> 272270 | E5: 円 | I5: 毎月返済額 | J5: =INT(PMT(J3/12,J4*12,-J2*10000)) -> 216829 | K5: 円
C6: 年間返済額 | D6: =D5*12 -> 3267240 | I6: 年間返済額 | J6: =J5*12 -> 2601948
C8: 毎月返済額 | D8: 利息 | E8: 元金 | F8: ローン残高 | I8: 毎月返済額 | J8: 利息 | K8: 元金 | L8: ローン残高
B9: 1 | C9: =D5 -> 272270 | D9: =INT(D2*10000*D3/12) -> 179166 | E9: =C9-D9 -> 93104 | F9: =D2*10000-E9 -> 49906896 | H9: 1 | I9: =J5 -> 216829 | J9: =INT(J2*10000*J3/12) -> 91666 | K9: =I9-J9 -> 125163 | L9: =J2*10000-K9 -> 49874837
B10: =B9+1 -> 2 | C10: =C9 -> 272270 | D10: =INT(F9*$D$3/12) -> 178833 | E10: =C10-D10 -> 93437 | F10: =F9-E10 -> 49813459 | H10: =H9+1 -> 2 | I10: =I9 -> 216829 | J10: =INT(L9*$J$3/12) -> 91437 | K10: =I10-J10 -> 125392 | L10: =L9-K10 -> 49749445
B11: =B10+1 -> 3 | C11: =C10 -> 272270 | D11: =INT(F10*$D$3/12) -> 178498 | E11: =C11-D11 -> 93772 | F11: =F10-E11 -> 49719687 | H11: =H10+1 -> 3 | I11: =I10 -> 216829 | J11: =INT(L10*$J$3/12) -> 91207 | K11: =I11-J11 -> 125622 | L11: =L10-K11 -> 49623823
B12: =B11+1 -> 4 | C12: =C11 -> 272270 | D12: =INT(F11*$D$3/12) -> 178162 | E12: =C12-D12 -> 94108 | F12: =F11-E12 -> 49625579 | H12: =H11+1 -> 4 | I12: =I11 -> 216829 | J12: =INT(L11*$J$3/12) -> 90977 | K12: =I12-J12 -> 125852 | L12: =L11-K12 -> 49497971
B13: =B12+1 -> 5 | C13: =C12 -> 272270 | D13: =INT(F12*$D$3/12) -> 177824 | E13: =C13-D13 -> 94446 | F13: =F12-E13 -> 49531133 | H13: =H12+1 -> 5 | I13: =I12 -> 216829 | J13: =INT(L12*$J$3/12) -> 90746 | K13: =I13-J13 -> 126083 | L13: =L12-K13 -> 49371888
B14: =B13+1 -> 6 | C14: =C13 -> 272270 | D14: =INT(F13*$D$3/12) -> 177486 | E14: =C14-D14 -> 94784 | F14: =F13-E14 -> 49436349 | H14: =H13+1 -> 6 | I14: =I13 -> 216829 | J14: =INT(L13*$J$3/12) -> 90515 | K14: =I14-J14 -> 126314 | L14: =L13-K14 -> 49245574
B15: =B14+1 -> 7 | C15: =C14 -> 272270 | D15: =INT(F14*$D$3/12) -> 177146 | E15: =C15-D15 -> 95124 | F15: =F14-E15 -> 49341225 | H15: =H14+1 -> 7 | I15: =I14 -> 216829 | J15: =INT(L14*$J$3/12) -> 90283 | K15: =I15-J15 -> 126546 | L15: =L14-K15 -> 49119028
B16: =B15+1 -> 8 | C16: =C15 -> 272270 | D16: =INT(F15*$D$3/12) -> 176806 | E16: =C16-D16 -> 95464 | F16: =F15-E16 -> 49245761 | H16: =H15+1 -> 8 | I16: =I15 -> 216829 | J16: =INT(L15*$J$3/12) -> 90051 | K16: =I16-J16 -> 126778 | L16: =L15-K16 -> 48992250
B17: =B16+1 -> 9 | C17: =C16 -> 272270 | D17: =INT(F16*$D$3/12) -> 176463 | E17: =C17-D17 -> 95807 | F17: =F16-E17 -> 49149954 | H17: =H16+1 -> 9 | I17: =I16 -> 216829 | J17: =INT(L16*$J$3/12) -> 89819 | K17: =I17-J17 -> 127010 | L17: =L16-K17 -> 48865240
B18: =B17+1 -> 10 | C18: =C17 -> 272270 | D18: =INT(F17*$D$3/12) -> 176120 | E18: =C18-D18 -> 96150 | F18: =F17-E18 -> 49053804 | H18: =H17+1 -> 10 | I18: =I17 -> 216829 | J18: =INT(L17*$J$3/12) -> 89586 | K18: =I18-J18 -> 127243 | L18: =L17-K18 -> 48737997
B19: =B18+1 -> 11 | C19: =C18 -> 272270 | D19: =INT(F18*$D$3/12) -> 175776 | E19: =C19-D19 -> 96494 | F19: =F18-E19 -> 48957310 | H19: =H18+1 -> 11 | I19: =I18 -> 216829 | J19: =INT(L18*$J$3/12) -> 89352 | K19: =I19-J19 -> 127477 | L19: =L18-K19 -> 48610520
B20: =B19+1 -> 12 | C20: =C19 -> 272270 | D20: =INT(F19*$D$3/12) -> 175430 | E20: =C20-D20 -> 96840 | F20: =F19-E20 -> 48860470 | H20: =H19+1 -> 12 | I20: =I19 -> 216829 | J20: =INT(L19*$J$3/12) -> 89119 | K20: =I20-J20 -> 127710 | L20: =L19-K20 -> 48482810
A21: ２年 | B21: =B20+1 -> 13 | C21: =C20 -> 272270 | D21: =INT(F20*$D$3/12) -> 175083 | E21: =C21-D21 -> 97187 | F21: =F20-E21 -> 48763283 | H21: =H20+1 -> 13 | I21: =I20 -> 216829 | J21: =INT(L20*$J$3/12) -> 88885 | K21: =I21-J21 -> 127944 | L21: =L20-K21 -> 48354866
B22: =B21+1 -> 14 | C22: =C21 -> 272270 | D22: =INT(F21*$D$3/12) -> 174735 | E22: =C22-D22 -> 97535 | F22: =F21-E22 -> 48665748 | H22: =H21+1 -> 14 | I22: =I21 -> 216829 | J22: =INT(L21*$J$3/12) -> 88650 | K22: =I22-J22 -> 128179 | L22: =L21-K22 -> 48226687
B23: =B22+1 -> 15 | C23: =C22 -> 272270 | D23: =INT(F22*$D$3/12) -> 174385 | E23: =C23-D23 -> 97885 | F23: =F22-E23 -> 48567863 | H23: =H22+1 -> 15 | I23: =I22 -> 216829 | J23: =INT(L22*$J$3/12) -> 88415 | K23: =I23-J23 -> 128414 | L23: =L22-K23 -> 48098273
B24: =B23+1 -> 16 | C24: =C23 -> 272270 | D24: =INT(F23*$D$3/12) -> 174034 | E24: =C24-D24 -> 98236 | F24: =F23-E24 -> 48469627 | H24: =H23+1 -> 16 | I24: =I23 -> 216829 | J24: =INT(L23*$J$3/12) -> 88180 | K24: =I24-J24 -> 128649 | L24: =L23-K24 -> 47969624
B25: =B24+1 -> 17 | C25: =C24 -> 272270 | D25: =INT(F24*$D$3/12) -> 173682 | E25: =C25-D25 -> 98588 | F25: =F24-E25 -> 48371039 | H25: =H24+1 -> 17 | I25: =I24 -> 216829 | J25: =INT(L24*$J$3/12) -> 87944 | K25: =I25-J25 -> 128885 | L25: =L24-K25 -> 47840739
B26: =B25+1 -> 18 | C26: =C25 -> 272270 | D26: =INT(F25*$D$3/12) -> 173329 | E26: =C26-D26 -> 98941 | F26: =F25-E26 -> 48272098 | H26: =H25+1 -> 18 | I26: =I25 -> 216829 | J26: =INT(L25*$J$3/12) -> 87708 | K26: =I26-J26 -> 129121 | L26: =L25-K26 -> 47711618
B27: =B26+1 -> 19 | C27: =C26 -> 272270 | D27: =INT(F26*$D$3/12) -> 172975 | E27: =C27-D27 -> 99295 | F27: =F26-E27 -> 48172803 | H27: =H26+1 -> 19 | I27: =I26 -> 216829 | J27: =INT(L26*$J$3/12) -> 87471 | K27: =I27-J27 -> 129358 | L27: =L26-K27 -> 47582260
B28: =B27+1 -> 20 | C28: =C27 -> 272270 | D28: =INT(F27*$D$3/12) -> 172619 | E28: =C28-D28 -> 99651 | F28: =F27-E28 -> 48073152 | H28: =H27+1 -> 20 | I28: =I27 -> 216829 | J28: =INT(L27*$J$3/12) -> 87234 | K28: =I28-J28 -> 129595 | L28: =L27-K28 -> 47452665
B29: =B28+1 -> 21 | C29: =C28 -> 272270 | D29: =INT(F28*$D$3/12) -> 172262 | E29: =C29-D29 -> 100008 | F29: =F28-E29 -> 47973144 | H29: =H28+1 -> 21 | I29: =I28 -> 216829 | J29: =INT(L28*$J$3/12) -> 86996 | K29: =I29-J29 -> 129833 | L29: =L28-K29 -> 47322832
B30: =B29+1 -> 22 | C30: =C29 -> 272270 | D30: =INT(F29*$D$3/12) -> 171903 | E30: =C30-D30 -> 100367 | F30: =F29-E30 -> 47872777 | H30: =H29+1 -> 22 | I30: =I29 -> 216829 | J30: =INT(L29*$J$3/12) -> 86758 | K30: =I30-J30 -> 130071 | L30: =L29-K30 -> 47192761
B31: =B30+1 -> 23 | C31: =C30 -> 272270 | D31: =INT(F30*$D$3/12) -> 171544 | E31: =C31-D31 -> 100726 | F31: =F30-E31 -> 47772051 | H31: =H30+1 -> 23 | I31: =I30 -> 216829 | J31: =INT(L30*$J$3/12) -> 86520 | K31: =I31-J31 -> 130309 | L31: =L30-K31 -> 47062452
B32: =B31+1 -> 24 | C32: =C31 -> 272270 | D32: =INT(F31*$D$3/12) -> 171183 | E32: =C32-D32 -> 101087 | F32: =F31-E32 -> 47670964 | H32: =H31+1 -> 24 | I32: =I31 -> 216829 | J32: =INT(L31*$J$3/12) -> 86281 | K32: =I32-J32 -> 130548 | L32: =L31-K32 -> 46931904
A33: ３年 | B33: =B32+1 -> 25 | C33: =C32 -> 272270 | D33: =INT(F32*$D$3/12) -> 170820 | E33: =C33-D33 -> 101450 | F33: =F32-E33 -> 47569514 | H33: =H32+1 -> 25 | I33: =I32 -> 216829 | J33: =INT(L32*$J$3/12) -> 86041 | K33: =I33-J33 -> 130788 | L33: =L32-K33 -> 46801116
B34: =B33+1 -> 26 | C34: =C33 -> 272270 | D34: =INT(F33*$D$3/12) -> 170457 | E34: =C34-D34 -> 101813 | F34: =F33-E34 -> 47467701 | H34: =H33+1 -> 26 | I34: =I33 -> 216829 | J34: =INT(L33*$J$3/12) -> 85802 | K34: =I34-J34 -> 131027 | L34: =L33-K34 -> 46670089
B35: =B34+1 -> 27 | C35: =C34 -> 272270 | D35: =INT(F34*$D$3/12) -> 170092 | E35: =C35-D35 -> 102178 | F35: =F34-E35 -> 47365523 | H35: =H34+1 -> 27 | I35: =I34 -> 216829 | J35: =INT(L34*$J$3/12) -> 85561 | K35: =I35-J35 -> 131268 | L35: =L34-K35 -> 46538821
B36: =B35+1 -> 28 | C36: =C35 -> 272270 | D36: =INT(F35*$D$3/12) -> 169726 | E36: =C36-D36 -> 102544 | F36: =F35-E36 -> 47262979 | H36: =H35+1 -> 28 | I36: =I35 -> 216829 | J36: =INT(L35*$J$3/12) -> 85321 | K36: =I36-J36 -> 131508 | L36: =L35-K36 -> 46407313
B37: =B36+1 -> 29 | C37: =C36 -> 272270 | D37: =INT(F36*$D$3/12) -> 169359 | E37: =C37-D37 -> 102911 | F37: =F36-E37 -> 47160068 | H37: =H36+1 -> 29 | I37: =I36 -> 216829 | J37: =INT(L36*$J$3/12) -> 85080 | K37: =I37-J37 -> 131749 | L37: =L36-K37 -> 46275564
B38: =B37+1 -> 30 | C38: =C37 -> 272270 | D38: =INT(F37*$D$3/12) -> 168990 | E38: =C38-D38 -> 103280 | F38: =F37-E38 -> 47056788 | H38: =H37+1 -> 30 | I38: =I37 -> 216829 | J38: =INT(L37*$J$3/12) -> 84838 | K38: =I38-J38 -> 131991 | L38: =L37-K38 -> 46143573
B39: =B38+1 -> 31 | C39: =C38 -> 272270 | D39: =INT(F38*$D$3/12) -> 168620 | E39: =C39-D39 -> 103650 | F39: =F38-E39 -> 46953138 | H39: =H38+1 -> 31 | I39: =I38 -> 216829 | J39: =INT(L38*$J$3/12) -> 84596 | K39: =I39-J39 -> 132233 | L39: =L38-K39 -> 46011340
B40: =B39+1 -> 32 | C40: =C39 -> 272270 | D40: =INT(F39*$D$3/12) -> 168248 | E40: =C40-D40 -> 104022 | F40: =F39-E40 -> 46849116 | H40: =H39+1 -> 32 | I40: =I39 -> 216829 | J40: =INT(L39*$J$3/12) -> 84354 | K40: =I40-J40 -> 132475 | L40: =L39-K40 -> 45878865
B41: =B40+1 -> 33 | C41: =C40 -> 272270 | D41: =INT(F40*$D$3/12) -> 167875 | E41: =C41-D41 -> 104395 | F41: =F40-E41 -> 46744721 | H41: =H40+1 -> 33 | I41: =I40 -> 216829 | J41: =INT(L40*$J$3/12) -> 84111 | K41: =I41-J41 -> 132718 | L41: =L40-K41 -> 45746147
B42: =B41+1 -> 34 | C42: =C41 -> 272270 | D42: =INT(F41*$D$3/12) -> 167501 | E42: =C42-D42 -> 104769 | F42: =F41-E42 -> 46639952 | H42: =H41+1 -> 34 | I42: =I41 -> 216829 | J42: =INT(L41*$J$3/12) -> 83867 | K42: =I42-J42 -> 132962 | L42: =L41-K42 -> 45613185
B43: =B42+1 -> 35 | C43: =C42 -> 272270 | D43: =INT(F42*$D$3/12) -> 167126 | E43: =C43-D43 -> 105144 | F43: =F42-E43 -> 46534808 | H43: =H42+1 -> 35 | I43: =I42 -> 216829 | J43: =INT(L42*$J$3/12) -> 83624 | K43: =I43-J43 -> 133205 | L43: =L42-K43 -> 45479980
B44: =B43+1 -> 36 | C44: =C43 -> 272270 | D44: =INT(F43*$D$3/12) -> 166749 | E44: =C44-D44 -> 105521 | F44: =F43-E44 -> 46429287 | H44: =H43+1 -> 36 | I44: =I43 -> 216829 | J44: =INT(L43*$J$3/12) -> 83379 | K44: =I44-J44 -> 133450 | L44: =L43-K44 -> 45346530
A45: ４年 | B45: =B44+1 -> 37 | C45: =C44 -> 272270 | D45: =INT(F44*$D$3/12) -> 166371 | E45: =C45-D45 -> 105899 | F45: =F44-E45 -> 46323388 | H45: =H44+1 -> 37 | I45: =I44 -> 216829 | J45: =INT(L44*$J$3/12) -> 83135 | K45: =I45-J45 -> 133694 | L45: =L44-K45 -> 45212836
B46: =B45+1 -> 38 | C46: =C45 -> 272270 | D46: =INT(F45*$D$3/12) -> 165992 | E46: =C46-D46 -> 106278 | F46: =F45-E46 -> 46217110 | H46: =H45+1 -> 38 | I46: =I45 -> 216829 | J46: =INT(L45*$J$3/12) -> 82890 | K46: =I46-J46 -> 133939 | L46: =L45-K46 -> 45078897
B47: =B46+1 -> 39 | C47: =C46 -> 272270 | D47: =INT(F46*$D$3/12) -> 165611 | E47: =C47-D47 -> 106659 | F47: =F46-E47 -> 46110451 | H47: =H46+1 -> 39 | I47: =I46 -> 216829 | J47: =INT(L46*$J$3/12) -> 82644 | K47: =I47-J47 -> 134185 | L47: =L46-K47 -> 44944712
B48: =B47+1 -> 40 | C48: =C47 -> 272270 | D48: =INT(F47*$D$3/12) -> 165229 | E48: =C48-D48 -> 107041 | F48: =F47-E48 -> 46003410 | H48: =H47+1 -> 40 | I48: =I47 -> 216829 | J48: =INT(L47*$J$3/12) -> 82398 | K48: =I48-J48 -> 134431 | L48: =L47-K48 -> 44810281
B49: =B48+1 -> 41 | C49: =C48 -> 272270 | D49: =INT(F48*$D$3/12) -> 164845 | E49: =C49-D49 -> 107425 | F49: =F48-E49 -> 45895985 | H49: =H48+1 -> 41 | I49: =I48 -> 216829 | J49: =INT(L48*$J$3/12) -> 82152 | K49: =I49-J49 -> 134677 | L49: =L48-K49 -> 44675604
B50: =B49+1 -> 42 | C50: =C49 -> 272270 | D50: =INT(F49*$D$3/12) -> 164460 | E50: =C50-D50 -> 107810 | F50: =F49-E50 -> 45788175 | H50: =H49+1 -> 42 | I50: =I49 -> 216829 | J50: =INT(L49*$J$3/12) -> 81905 | K50: =I50-J50 -> 134924 | L50: =L49-K50 -> 44540680
B51: =B50+1 -> 43 | C51: =C50 -> 272270 | D51: =INT(F50*$D$3/12) -> 164074 | E51: =C51-D51 -> 108196 | F51: =F50-E51 -> 45679979 | H51: =H50+1 -> 43 | I51: =I50 -> 216829 | J51: =INT(L50*$J$3/12) -> 81657 | K51: =I51-J51 -> 135172 | L51: =L50-K51 -> 44405508
B52: =B51+1 -> 44 | C52: =C51 -> 272270 | D52: =INT(F51*$D$3/12) -> 163686 | E52: =C52-D52 -> 108584 | F52: =F51-E52 -> 45571395 | H52: =H51+1 -> 44 | I52: =I51 -> 216829 | J52: =INT(L51*$J$3/12) -> 81410 | K52: =I52-J52 -> 135419 | L52: =L51-K52 -> 44270089
B53: =B52+1 -> 45 | C53: =C52 -> 272270 | D53: =INT(F52*$D$3/12) -> 163297 | E53: =C53-D53 -> 108973 | F53: =F52-E53 -> 45462422 | H53: =H52+1 -> 45 | I53: =I52 -> 216829 | J53: =INT(L52*$J$3/12) -> 81161 | K53: =I53-J53 -> 135668 | L53: =L52-K53 -> 44134421
B54: =B53+1 -> 46 | C54: =C53 -> 272270 | D54: =INT(F53*$D$3/12) -> 162907 | E54: =C54-D54 -> 109363 | F54: =F53-E54 -> 45353059 | H54: =H53+1 -> 46 | I54: =I53 -> 216829 | J54: =INT(L53*$J$3/12) -> 80913 | K54: =I54-J54 -> 135916 | L54: =L53-K54 -> 43998505
B55: =B54+1 -> 47 | C55: =C54 -> 272270 | D55: =INT(F54*$D$3/12) -> 162515 | E55: =C55-D55 -> 109755 | F55: =F54-E55 -> 45243304 | H55: =H54+1 -> 47 | I55: =I54 -> 216829 | J55: =INT(L54*$J$3/12) -> 80663 | K55: =I55-J55 -> 136166 | L55: =L54-K55 -> 43862339
B56: =B55+1 -> 48 | C56: =C55 -> 272270 | D56: =INT(F55*$D$3/12) -> 162121 | E56: =C56-D56 -> 110149 | F56: =F55-E56 -> 45133155 | H56: =H55+1 -> 48 | I56: =I55 -> 216829 | J56: =INT(L55*$J$3/12) -> 80414 | K56: =I56-J56 -> 136415 | L56: =L55-K56 -> 43725924
A57: ５年目 | B57: =B56+1 -> 49 | C57: =C56 -> 272270 | D57: =INT(F56*$D$3/12) -> 161727 | E57: =C57-D57 -> 110543 | F57: =F56-E57 -> 45022612 | H57: =H56+1 -> 49 | I57: =I56 -> 216829 | J57: =INT(L56*$J$3/12) -> 80164 | K57: =I57-J57 -> 136665 | L57: =L56-K57 -> 43589259
B58: =B57+1 -> 50 | C58: =C57 -> 272270 | D58: =INT(F57*$D$3/12) -> 161331 | E58: =C58-D58 -> 110939 | F58: =F57-E58 -> 44911673 | H58: =H57+1 -> 50 | I58: =I57 -> 216829 | J58: =INT(L57*$J$3/12) -> 79913 | K58: =I58-J58 -> 136916 | L58: =L57-K58 -> 43452343
B59: =B58+1 -> 51 | C59: =C58 -> 272270 | D59: =INT(F58*$D$3/12) -> 160933 | E59: =C59-D59 -> 111337 | F59: =F58-E59 -> 44800336 | H59: =H58+1 -> 51 | I59: =I58 -> 216829 | J59: =INT(L58*$J$3/12) -> 79662 | K59: =I59-J59 -> 137167 | L59: =L58-K59 -> 43315176
B60: =B59+1 -> 52 | C60: =C59 -> 272270 | D60: =INT(F59*$D$3/12) -> 160534 | E60: =C60-D60 -> 111736 | F60: =F59-E60 -> 44688600 | H60: =H59+1 -> 52 | I60: =I59 -> 216829 | J60: =INT(L59*$J$3/12) -> 79411 | K60: =I60-J60 -> 137418 | L60: =L59-K60 -> 43177758
B61: =B60+1 -> 53 | C61: =C60 -> 272270 | D61: =INT(F60*$D$3/12) -> 160134 | E61: =C61-D61 -> 112136 | F61: =F60-E61 -> 44576464 | H61: =H60+1 -> 53 | I61: =I60 -> 216829 | J61: =INT(L60*$J$3/12) -> 79159 | K61: =I61-J61 -> 137670 | L61: =L60-K61 -> 43040088
B62: =B61+1 -> 54 | C62: =C61 -> 272270 | D62: =INT(F61*$D$3/12) -> 159732 | E62: =C62-D62 -> 112538 | F62: =F61-E62 -> 44463926 | H62: =H61+1 -> 54 | I62: =I61 -> 216829 | J62: =INT(L61*$J$3/12) -> 78906 | K62: =I62-J62 -> 137923 | L62: =L61-K62 -> 42902165
B63: =B62+1 -> 55 | C63: =C62 -> 272270 | D63: =INT(F62*$D$3/12) -> 159329 | E63: =C63-D63 -> 112941 | F63: =F62-E63 -> 44350985 | H63: =H62+1 -> 55 | I63: =I62 -> 216829 | J63: =INT(L62*$J$3/12) -> 78653 | K63: =I63-J63 -> 138176 | L63: =L62-K63 -> 42763989
B64: =B63+1 -> 56 | C64: =C63 -> 272270 | D64: =INT(F63*$D$3/12) -> 158924 | E64: =C64-D64 -> 113346 | F64: =F63-E64 -> 44237639 | H64: =H63+1 -> 56 | I64: =I63 -> 216829 | J64: =INT(L63*$J$3/12) -> 78400 | K64: =I64-J64 -> 138429 | L64: =L63-K64 -> 42625560
B65: =B64+1 -> 57 | C65: =C64 -> 272270 | D65: =INT(F64*$D$3/12) -> 158518 | E65: =C65-D65 -> 113752 | F65: =F64-E65 -> 44123887 | H65: =H64+1 -> 57 | I65: =I64 -> 216829 | J65: =INT(L64*$J$3/12) -> 78146 | K65: =I65-J65 -> 138683 | L65: =L64-K65 -> 42486877
B66: =B65+1 -> 58 | C66: =C65 -> 272270 | D66: =INT(F65*$D$3/12) -> 158110 | E66: =C66-D66 -> 114160 | F66: =F65-E66 -> 44009727 | H66: =H65+1 -> 58 | I66: =I65 -> 216829 | J66: =INT(L65*$J$3/12) -> 77892 | K66: =I66-J66 -> 138937 | L66: =L65-K66 -> 42347940
B67: =B66+1 -> 59 | C67: =C66 -> 272270 | D67: =INT(F66*$D$3/12) -> 157701 | E67: =C67-D67 -> 114569 | F67: =F66-E67 -> 43895158 | H67: =H66+1 -> 59 | I67: =I66 -> 216829 | J67: =INT(L66*$J$3/12) -> 77637 | K67: =I67-J67 -> 139192 | L67: =L66-K67 -> 42208748
B68: =B67+1 -> 60 | C68: =C67 -> 272270 | D68: =INT(F67*$D$3/12) -> 157290 | E68: =C68-D68 -> 114980 | F68: =F67-E68 -> 43780178 | H68: =H67+1 -> 60 | I68: =I67 -> 216829 | J68: =INT(L67*$J$3/12) -> 77382 | K68: =I68-J68 -> 139447 | L68: =L67-K68 -> 42069301
A69: ６年目 | B69: =B68+1 -> 61 | C69: =C68 -> 272270 | D69: =INT(F68*$D$3/12) -> 156878 | E69: =C69-D69 -> 115392 | F69: =F68-E69 -> 43664786 | H69: =H68+1 -> 61 | I69: =I68 -> 216829 | J69: =INT(L68*$J$3/12) -> 77127 | K69: =I69-J69 -> 139702 | L69: =L68-K69 -> 41929599
B70: =B69+1 -> 62 | C70: =C69 -> 272270 | D70: =INT(F69*$D$3/12) -> 156465 | E70: =C70-D70 -> 115805 | F70: =F69-E70 -> 43548981 | H70: =H69+1 -> 62 | I70: =I69 -> 216829 | J70: =INT(L69*$J$3/12) -> 76870 | K70: =I70-J70 -> 139959 | L70: =L69-K70 -> 41789640
B71: =B70+1 -> 63 | C71: =C70 -> 272270 | D71: =INT(F70*$D$3/12) -> 156050 | E71: =C71-D71 -> 116220 | F71: =F70-E71 -> 43432761 | H71: =H70+1 -> 63 | I71: =I70 -> 216829 | J71: =INT(L70*$J$3/12) -> 76614 | K71: =I71-J71 -> 140215 | L71: =L70-K71 -> 41649425
B72: =B71+1 -> 64 | C72: =C71 -> 272270 | D72: =INT(F71*$D$3/12) -> 155634 | E72: =C72-D72 -> 116636 | F72: =F71-E72 -> 43316125 | H72: =H71+1 -> 64 | I72: =I71 -> 216829 | J72: =INT(L71*$J$3/12) -> 76357 | K72: =I72-J72 -> 140472 | L72: =L71-K72 -> 41508953
B73: =B72+1 -> 65 | C73: =C72 -> 272270 | D73: =INT(F72*$D$3/12) -> 155216 | E73: =C73-D73 -> 117054 | F73: =F72-E73 -> 43199071 | H73: =H72+1 -> 65 | I73: =I72 -> 216829 | J73: =INT(L72*$J$3/12) -> 76099 | K73: =I73-J73 -> 140730 | L73: =L72-K73 -> 41368223
B74: =B73+1 -> 66 | C74: =C73 -> 272270 | D74: =INT(F73*$D$3/12) -> 154796 | E74: =C74-D74 -> 117474 | F74: =F73-E74 -> 43081597 | H74: =H73+1 -> 66 | I74: =I73 -> 216829 | J74: =INT(L73*$J$3/12) -> 75841 | K74: =I74-J74 -> 140988 | L74: =L73-K74 -> 41227235
B75: =B74+1 -> 67 | C75: =C74 -> 272270 | D75: =INT(F74*$D$3/12) -> 154375 | E75: =C75-D75 -> 117895 | F75: =F74-E75 -> 42963702 | H75: =H74+1 -> 67 | I75: =I74 -> 216829 | J75: =INT(L74*$J$3/12) -> 75583 | K75: =I75-J75 -> 141246 | L75: =L74-K75 -> 41085989
B76: =B75+1 -> 68 | C76: =C75 -> 272270 | D76: =INT(F75*$D$3/12) -> 153953 | E76: =C76-D76 -> 118317 | F76: =F75-E76 -> 42845385 | H76: =H75+1 -> 68 | I76: =I75 -> 216829 | J76: =INT(L75*$J$3/12) -> 75324 | K76: =I76-J76 -> 141505 | L76: =L75-K76 -> 40944484
B77: =B76+1 -> 69 | C77: =C76 -> 272270 | D77: =INT(F76*$D$3/12) -> 153529 | E77: =C77-D77 -> 118741 | F77: =F76-E77 -> 42726644 | H77: =H76+1 -> 69 | I77: =I76 -> 216829 | J77: =INT(L76*$J$3/12) -> 75064 | K77: =I77-J77 -> 141765 | L77: =L76-K77 -> 40802719
B78: =B77+1 -> 70 | C78: =C77 -> 272270 | D78: =INT(F77*$D$3/12) -> 153103 | E78: =C78-D78 -> 119167 | F78: =F77-E78 -> 42607477 | H78: =H77+1 -> 70 | I78: =I77 -> 216829 | J78: =INT(L77*$J$3/12) -> 74804 | K78: =I78-J78 -> 142025 | L78: =L77-K78 -> 40660694
B79: =B78+1 -> 71 | C79: =C78 -> 272270 | D79: =INT(F78*$D$3/12) -> 152676 | E79: =C79-D79 -> 119594 | F79: =F78-E79 -> 42487883 | H79: =H78+1 -> 71 | I79: =I78 -> 216829 | J79: =INT(L78*$J$3/12) -> 74544 | K79: =I79-J79 -> 142285 | L79: =L78-K79 -> 40518409
B80: =B79+1 -> 72 | C80: =C79 -> 272270 | D80: =INT(F79*$D$3/12) -> 152248 | E80: =C80-D80 -> 120022 | F80: =F79-E80 -> 42367861 | H80: =H79+1 -> 72 | I80: =I79 -> 216829 | J80: =INT(L79*$J$3/12) -> 74283 | K80: =I80-J80 -> 142546 | L80: =L79-K80 -> 40375863
B81: =B80+1 -> 73 | C81: =C80 -> 272270 | D81: =INT(F80*$D$3/12) -> 151818 | E81: =C81-D81 -> 120452 | F81: =F80-E81 -> 42247409 | H81: =H80+1 -> 73 | I81: =I80 -> 216829 | J81: =INT(L80*$J$3/12) -> 74022 | K81: =I81-J81 -> 142807 | L81: =L80-K81 -> 40233056
... B368: =B367+1 -> 360 | C368: =C367 -> 272270 | D368: =INT(F367*$D$3/12) -> -63972 | E368: =C368-D368 -> 336242 | F368: =F367-E368 -> -18188890 | H368: =H367+1 -> 360 | I368: =I367 -> 216829 | J368: =INT(L367*$J$3/12) -> -24746 | K368: =I368-J368 -> 241575 | L368: =L367-K368 -> -13739074
